odoo/addons/stock_checkout_sync/README.rst
odoo/addons/stock_checkout_sync/__init__.py
odoo/addons/stock_checkout_sync/__manifest__.py
odoo/addons/stock_checkout_sync/i18n/es_AR.po
odoo/addons/stock_checkout_sync/i18n/stock_checkout_sync.pot
odoo/addons/stock_checkout_sync/models/__init__.py
odoo/addons/stock_checkout_sync/models/stock_move.py
odoo/addons/stock_checkout_sync/models/stock_picking.py
odoo/addons/stock_checkout_sync/models/stock_picking_type.py
odoo/addons/stock_checkout_sync/readme/CONFIGURE.rst
odoo/addons/stock_checkout_sync/readme/CONTRIBUTORS.rst
odoo/addons/stock_checkout_sync/readme/CREDITS.rst
odoo/addons/stock_checkout_sync/readme/DESCRIPTION.rst
odoo/addons/stock_checkout_sync/security/ir.model.access.csv
odoo/addons/stock_checkout_sync/static/description/icon.png
odoo/addons/stock_checkout_sync/static/description/index.html
odoo/addons/stock_checkout_sync/static/description/sync-assistant.png
odoo/addons/stock_checkout_sync/tests/__init__.py
odoo/addons/stock_checkout_sync/tests/common.py
odoo/addons/stock_checkout_sync/tests/test_checkout_sync.py
odoo/addons/stock_checkout_sync/views/stock_picking_type_views.xml
odoo/addons/stock_checkout_sync/views/stock_picking_views.xml
odoo/addons/stock_checkout_sync/wizards/__init__.py
odoo/addons/stock_checkout_sync/wizards/stock_move_checkout_sync.py
odoo/addons/stock_checkout_sync/wizards/stock_move_checkout_sync_views.xml
odoo14_addon_stock_checkout_sync-14.0.1.1.0.dist-info/METADATA
odoo14_addon_stock_checkout_sync-14.0.1.1.0.dist-info/WHEEL
odoo14_addon_stock_checkout_sync-14.0.1.1.0.dist-info/top_level.txt
odoo14_addon_stock_checkout_sync-14.0.1.1.0.dist-info/RECORD
